pytensorlab/__init__.py
pytensorlab/_external/__init__.py
pytensorlab/_external/_stub_pymanopt.py
pytensorlab/algorithms/TensorOptimizationKernel.py
pytensorlab/algorithms/__init__.py
pytensorlab/algorithms/cpd.py
pytensorlab/algorithms/cpd_gevd.py
pytensorlab/algorithms/cpd_opt.py
pytensorlab/algorithms/gentensor_mlsv.py
pytensorlab/algorithms/lmlra.py
pytensorlab/algorithms/lra.py
pytensorlab/algorithms/mlsvd.py
pytensorlab/algorithms/optimization_default_settings.py
pytensorlab/algorithms/tt.py
pytensorlab/backends/__init__.py
pytensorlab/backends/numpy.py
pytensorlab/backends/numpy.pyi
pytensorlab/datatypes/__init__.py
pytensorlab/datatypes/binops.py
pytensorlab/datatypes/core.py
pytensorlab/datatypes/deferred_residual.py
pytensorlab/datatypes/hankel.py
pytensorlab/datatypes/ndarray.py
pytensorlab/datatypes/operators.py
pytensorlab/datatypes/partial.py
pytensorlab/datatypes/polyadic.py
pytensorlab/datatypes/tensor.py
pytensorlab/datatypes/tensortrain.py
pytensorlab/datatypes/tucker.py
pytensorlab/optimization/__init__.py
pytensorlab/optimization/logger.py
pytensorlab/optimization/methods.py
pytensorlab/optimization/printer.py
pytensorlab/optimization/problem.py
pytensorlab/optimization/protocols.py
pytensorlab/optimization/trust_region.py
pytensorlab/py.typed
pytensorlab/random/__init__.py
pytensorlab/random/_utils.py
pytensorlab/random/rng.py
pytensorlab/random/utils.py
pytensorlab/tensorization/__init__.py
pytensorlab/tensorization/statistics.py
pytensorlab/typing/__init__.py
pytensorlab/typing/core.py
pytensorlab/typing/validators.py
pytensorlab/util/__init__.py
pytensorlab/util/_lazy_loader.py
pytensorlab/util/exceptions.py
pytensorlab/util/indextricks.py
pytensorlab/util/options.py
pytensorlab/util/utils.py
pytensorlab/visualization/__init__.py
pytensorlab/visualization/_vedo_settings.py
pytensorlab/visualization/configure_matplotlib.py
pytensorlab/visualization/plot_convergence.py
pytensorlab/visualization/plot_rank1_terms.py
pytensorlab-2025.12.0.dist-info/METADATA
pytensorlab-2025.12.0.dist-info/WHEEL
pytensorlab-2025.12.0.dist-info/licenses/LICENSE.md
pytensorlab-2025.12.0.dist-info/RECORD
