Metadata-Version: 2.4
Name: pyTensorlab
Version: 2025.12.0
Summary: A Python package for tensor computations.
License-File: LICENSE.md
Keywords: tensor,array,tensor decomposition,visualization,complex optimization
Author: Nico Vervliet
Author-email: Nico.Vervliet@kuleuven.be
Maintainer: Nico Vervliet
Maintainer-email: Nico.Vervliet@kuleuven.be
Requires-Python: >=3.10
Classifier: Development Status :: 5 - Production/Stable
Classifier: Intended Audience :: Science/Research
Classifier: Programming Language :: Python :: 3
Classifier: Programming Language :: Python :: 3.10
Classifier: Programming Language :: Python :: 3.11
Classifier: Programming Language :: Python :: 3.12
Classifier: Programming Language :: Python :: 3.13
Classifier: Programming Language :: Python :: 3.14
Classifier: Topic :: Scientific/Engineering
Classifier: Topic :: Scientific/Engineering :: Artificial Intelligence
Classifier: Topic :: Scientific/Engineering :: Mathematics
Classifier: Typing :: Typed
Requires-Dist: multipledispatch (>=0.6)
Requires-Dist: numba (>=0.57.0)
Requires-Dist: numpy (>=2.0)
Requires-Dist: pymanopt (>=2.0.1)
Requires-Dist: scipy (>=1.13)
Requires-Dist: typing-extensions (>=4.3.0)
Requires-Dist: vedo (>=2023.4.5)
Project-URL: Bug Tracker, https://gitlab.esat.kuleuven.be/tensorgroup-public/pytensorlab-public/-/issues
Project-URL: Documentation, https://www.pytensorlab.net/docs/
Project-URL: Homepage, https://www.pytensorlab.net/
Project-URL: Repository, https://gitlab.esat.kuleuven.be/tensorgroup-public/pytensorlab-public
